samgis/__init__.py
samgis/__version__.py
samgis/io/__init__.py
samgis/io/coordinates_pixel_conversion.py
samgis/io/geo_helpers.py
samgis/io/raster_helpers.py
samgis/io/tms2geotiff.py
samgis/io/wrappers_helpers.py
samgis/prediction_api/__init__.py
samgis/prediction_api/predictors.py
samgis/utilities/__init__.py
samgis/utilities/constants.py
samgis/utilities/type_hints.py
samgis-1.5.4.dist-info/LICENSE.txt
samgis-1.5.4.dist-info/METADATA
samgis-1.5.4.dist-info/WHEEL
samgis-1.5.4.dist-info/RECORD
