Metadata-Version: 2.1
Name: samgis
Version: 1.5.4
Summary: A backend for machine learning instance segmentation on geospatial data even without dedicated graphics cards.
License: MIT
Author: alessandro trinca tornidor
Author-email: alessandro@trinca.tornidor.com
Requires-Python: >=3.10,<3.12
Classifier: License :: OSI Approved :: MIT License
Classifier: Programming Language :: Python :: 3
Classifier: Programming Language :: Python :: 3.10
Classifier: Programming Language :: Python :: 3.11
Requires-Dist: bson (>=0.5.10,<0.6.0)
Requires-Dist: contextily (>=1.6.0,<2.0.0)
Requires-Dist: geopandas (>=1.0.1,<2.0.0)
Requires-Dist: loguru (>=0.7.2,<0.8.0)
Requires-Dist: numpy (==1.25.2) ; python_version >= "3.10" and python_version < "3.11"
Requires-Dist: numpy (>=1.26,<2.0) ; python_version >= "3.11" and python_version < "3.12"
Requires-Dist: pillow (>=10.4.0,<11.0.0)
Requires-Dist: python-dotenv (>=1.0.1,<2.0.0)
Requires-Dist: rasterio (>=1.3.10,<2.0.0)
Requires-Dist: requests (>=2.32.3,<3.0.0)
Requires-Dist: samgis-core (==2.0.2)
Project-URL: Demo, https://huggingface.co/spaces/aletrn/samgis
Project-URL: Source, https://github.com/trincadev/samgis-be
